agent_mafia/__init__.py
agent_mafia/_modidx.py
agent_mafia/core.py
agent_mafia/client/MafiaError.py
agent_mafia/client/ResponseGetData.py
agent_mafia/client/__init__.py
agent_mafia/routes/__init__.py
agent_mafia/routes/domo.py
agent_mafia/utils/__init__.py
agent_mafia/utils/chunking.py
agent_mafia/utils/files.py
agent_mafia-0.0.3.dist-info/LICENSE
agent_mafia-0.0.3.dist-info/METADATA
agent_mafia-0.0.3.dist-info/WHEEL
agent_mafia-0.0.3.dist-info/entry_points.txt
agent_mafia-0.0.3.dist-info/top_level.txt
agent_mafia-0.0.3.dist-info/RECORD
